Workbook

Sheet Sales_Data
A1: Order ID | B1: Order Date | C1: Customer ID | D1: Customer Name | E1: State | F1: Category | G1: Product | H1: Salesperson | I1: Quantity | J1: Unit Price | K1: Discount(%) | L1: Sales | M1: Profit
A2: ORD001 | B2: 46023 | C2: C001 | D2: =_xlfn.XLOOKUP(C2,Lookup!M2:M11,Lookup!N2:N11,"Not Found") -> Amit Sharma | E2: Karnataka | F2: Electronics | G2: Laptop | H2: Rahul | I2: 1 | J2: =_xlfn.XLOOKUP(G2,Lookup!$B:$B,Lookup!$C:$C,"Not Found") -> 65000 | K2: 0.1 | L2: =I2*J2*(1-K2) -> 58500 | M2: =L2*_xlfn.XLOOKUP(G2,Lookup!$B:$B,Lookup!$D:$D) -> 10530
A3: ORD002 | B3: 46024 | C3: C002 | D3: =_xlfn.XLOOKUP(C3,Lookup!M3:M12,Lookup!N3:N12,"Not Found") -> Priya Nair | E3: TamilNadu | F3: Grocery | G3: Rice | H3: Priya | I3: 3 | J3: =_xlfn.XLOOKUP(G3,Lookup!$B:$B,Lookup!$C:$C,"Not Found") -> 1200 | K3: 0.05 | L3: =I3*J3*(1-K3) -> 3420 | M3: =L3*_xlfn.XLOOKUP(G3,Lookup!$B:$B,Lookup!$D:$D) -> 342
A4: ORD003 | B4: 46025 | C4: C003 | D4: =_xlfn.XLOOKUP(C4,Lookup!M4:M13,Lookup!N4:N13,"Not Found") -> Ravi Kumar | E4: Kerala | F4: Clothing | G4: T-Shirt | H4: Arjun | I4: 2 | J4: =_xlfn.XLOOKUP(G4,Lookup!$B:$B,Lookup!$C:$C,"Not Found") -> 799 | K4: 0.15 | L4: =I4*J4*(1-K4) -> 1358.3 | M4: =L4*_xlfn.XLOOKUP(G4,Lookup!$B:$B,Lookup!$D:$D) -> 339.575
A5: ORD004 | B5: 46026 | C5: C004 | D5: =_xlfn.XLOOKUP(C5,Lookup!M5:M14,Lookup!N5:N14,"Not Found") -> Sneha Reddy | E5: Telangana | F5: Electronics | G5: Smartphone | H5: Sneha | I5: 1 | J5: =_xlfn.XLOOKUP(G5,Lookup!$B:$B,Lookup!$C:$C,"Not Found") -> 25000 | K5: 0.08 | L5: =I5*J5*(1-K5) -> 23000 | M5: =L5*_xlfn.XLOOKUP(G5,Lookup!$B:$B,Lookup!$D:$D) -> 3450
A6: ORD005 | B6: 46027 | C6: C005 | D6: =_xlfn.XLOOKUP(C6,Lookup!M6:M15,Lookup!N6:N15,"Not Found") -> Arjun Singh | E6: Maharashtra | F6: Grocery | G6: Sugar | H6: Kiran | I6: 5 | J6: =_xlfn.XLOOKUP(G6,Lookup!$B:$B,Lookup!$C:$C,"Not Found") -> 60 | K6: 0 | L6: =I6*J6*(1-K6) -> 300 | M6: =L6*_xlfn.XLOOKUP(G6,Lookup!$B:$B,Lookup!$D:$D) -> 24
A7: ORD006 | B7: 46028 | C7: C006 | D7: =_xlfn.XLOOKUP(C7,Lookup!M7:M16,Lookup!N7:N16,"Not Found") -> Neha Patel | E7: Karnataka | F7: Clothing | G7: Jeans | H7: Neha | I7: 2 | J7: =_xlfn.XLOOKUP(G7,Lookup!$B:$B,Lookup!$C:$C,"Not Found") -> 1999 | K7: 0.1 | L7: =I7*J7*(1-K7) -> 3598.2 | M7: =L7*_xlfn.XLOOKUP(G7,Lookup!$B:$B,Lookup!$D:$D) -> 1079.46
A8: ORD007 | B8: 46029 | C8: C007 | D8: =_xlfn.XLOOKUP(C8,Lookup!M8:M17,Lookup!N8:N17,"Not Found") -> Kiran Das | E8: Delhi | F8: Electronics | G8: Printer | H8: Rohan | I8: 1 | J8: =_xlfn.XLOOKUP(G8,Lookup!$B:$B,Lookup!$C:$C,"Not Found") -> 12000 | K8: 0.12 | L8: =I8*J8*(1-K8) -> 10560 | M8: =L8*_xlfn.XLOOKUP(G8,Lookup!$B:$B,Lookup!$D:$D) -> 1584
A9: ORD008 | B9: 46030 | C9: C008 | D9: =_xlfn.XLOOKUP(C9,Lookup!M9:M18,Lookup!N9:N18,"Not Found") -> Anjali Verma | E9: Gujarat | F9: Grocery | G9: Tea Powder | H9: Anjali | I9: 4 | J9: =_xlfn.XLOOKUP(G9,Lookup!$B:$B,Lookup!$C:$C,"Not Found") -> 350 | K9: 0.05 | L9: =I9*J9*(1-K9) -> 1330 | M9: =L9*_xlfn.XLOOKUP(G9,Lookup!$B:$B,Lookup!$D:$D) -> 199.5
A10: ORD009 | B10: 46031 | C10: C009 | D10: =_xlfn.XLOOKUP(C10,Lookup!M10:M19,Lookup!N10:N19,"Not Found") -> Rohith Jain | E10: Rajasthan | F10: Clothing | G10: Shoes | H10: Rahul | I10: 2 | J10: =_xlfn.XLOOKUP(G10,Lookup!$B:$B,Lookup!$C:$C,"Not Found") -> 2499 | K10: 0.2 | L10: =I10*J10*(1-K10) -> 3998.4 | M10: =L10*_xlfn.XLOOKUP(G10,Lookup!$B:$B,Lookup!$D:$D) -> 1119.552
A11: ORD010 | B11: 46032 | C11: C010 | D11: =_xlfn.XLOOKUP(C11,Lookup!M11:M20,Lookup!N11:N20,"Not Found") -> Meera Iyer | E11: Andhra Pradesh | F11: Electronics | G11: Smartwatch | H11: Priya | I11: 3 | J11: =_xlfn.XLOOKUP(G11,Lookup!$B:$B,Lookup!$C:$C,"Not Found") -> 5000 | K11: 0.1 | L11: =I11*J11*(1-K11) -> 13500 | M11: =L11*_xlfn.XLOOKUP(G11,Lookup!$B:$B,Lookup!$D:$D) -> 2430
A12: ORD011 | B12: 46033 | C12: C011 | D12: =_xlfn.XLOOKUP(C12,Lookup!M12:M21,Lookup!N12:N21,"Not Found") -> Akash Kumar | E12: Karnataka | F12: Electronics | G12: Laptop | H12: Rahul | I12: 1 | J12: =_xlfn.XLOOKUP(G12,Lookup!$B:$B,Lookup!$C:$C,"Not Found") -> 65000 | K12: 0.1 | L12: =I12*J12*(1-K12) -> 58500 | M12: =L12*_xlfn.XLOOKUP(G12,Lookup!$B:$B,Lookup!$D:$D) -> 10530
A13: ORD012 | B13: 46034 | C13: C012 | D13: =_xlfn.XLOOKUP(C13,Lookup!M13:M22,Lookup!N13:N22,"Not Found") -> Divya Rao | E13: TamilNadu | F13: Grocery | G13: Rice | H13: Priya | I13: 3 | J13: =_xlfn.XLOOKUP(G13,Lookup!$B:$B,Lookup!$C:$C,"Not Found") -> 1200 | K13: 0.05 | L13: =I13*J13*(1-K13) -> 3420 | M13: =L13*_xlfn.XLOOKUP(G13,Lookup!$B:$B,Lookup!$D:$D) -> 342
... A101: ORD100 | B101: 46122 | C101: C100 | D101: =_xlfn.XLOOKUP(C101,Lookup!M101:M110,Lookup!N101:N110,"Not Found") -> Divya Sharma | E101: Andhra Pradesh | F101: Electronics | G101: Smartwatch | H101: Priya | I101: 3 | J101: =_xlfn.XLOOKUP(G101,Lookup!$B:$B,Lookup!$C:$C,"Not Found") -> 5000 | K101: 0.1 | L101: =I101*J101*(1-K101) -> 13500 | M101: =L101*_xlfn.XLOOKUP(G101,Lookup!$B:$B,Lookup!$D:$D) -> 2430

Sheet Lookup
A1: Category | B1: Product | C1: Unit Price | D1: Profit (%) | G1: States | J1: Salesperson | M1: Customer ID | N1: Customer Name
A2: Electronics | B2: Laptop | C2: 65000 | D2: 0.18 | G2: Karnataka | J2: Rahul | M2: C001 | N2: Amit Sharma
A3: Electronics | B3: Smartphone | C3: 25000 | D3: 0.15 | G3: Tamil Nadu | J3: Priya | M3: C002 | N3: Priya Nair
A4: Electronics | B4: Headphone | C4: 2500 | D4: 0.2 | G4: Kerala | J4: Arjun | M4: C003 | N4: Ravi Kumar
A5: Electronics | B5: Smartwatch | C5: 5000 | D5: 0.18 | G5: Andhra Pradesh | J5: Sneha | M5: C004 | N5: Sneha Reddy
A6: Electronics | B6: Printer | C6: 12000 | D6: 0.15 | G6: Telangana | J6: Kiran | M6: C005 | N6: Arjun Singh
A7: Grocery | B7: Rice | C7: 1200 | D7: 0.1 | G7: Maharashtra | J7: Neha | M7: C006 | N7: Neha Patel
A8: Grocery | B8: Sugar | C8: 60 | D8: 0.08 | G8: Delhi | J8: Rohan | M8: C007 | N8: Kiran Das
A9: Grocery | B9: Cooking Oil | C9: 180 | D9: 0.12 | G9: Gujarat | J9: Anjali | M9: C008 | N9: Anjali Verma
A10: Grocery | B10: Wheat Flour | C10: 55 | D10: 0.1 | G10: Rajasthan | M10: C009 | N10: Rohith Jain
A11: Grocery | B11: Tea Powder | C11: 350 | D11: 0.15 | G11: West Bengal | M11: C010 | N11: Meera Iyer
A12: Clothing | B12: T-Shirt | C12: 799 | D12: 0.25 | M12: C011 | N12: Akash Kumar
A13: Clothing | B13: Jeans | C13: 1999 | D13: 0.3 | M13: C012 | N13: Divya Rao
A14: Clothing | B14: Jacket | C14: 2999 | D14: 0.35 | M14: C013 | N14: Sanjay Patel
A15: Clothing | B15: Shoes | C15: 2499 | D15: 0.28 | M15: C014 | N15: Pooja Sharma
A16: Clothing | B16: Hoodie | C16: 1499 | D16: 0.3 | M16: C015 | N16: Vikram Singh
M17: C016 | N17: Nisha Reddy
M18: C017 | N18: Karthik Nair
M19: C018 | N19: Deepa Das
M20: C019 | N20: Manoj Verma
M21: C020 | N21: Aisha Khan
M22: C021 | N22: Rohan Mehta
M23: C022 | N23: Kavya Iyer
M24: C023 | N24: Aditya Joshi
M25: C024 | N25: Shruthi Rao
M26: C025 | N26: Harish Kumar
M27: C026 | N27: Pooja Nair
M28: C027 | N28: Naveen Kumar
... M101: C100 | N101: Divya Sharma

Sheet Pivot_Quantity_Product
A1: Product | B1: Sum - Quantity
A2: Jeans | B2: 20
A3: Laptop | B3: 10
A4: Printer | B4: 10
A5: Rice | B5: 30
A6: Shoes | B6: 20
A7: Smartphone | B7: 10
A8: Smartwatch | B8: 30
A9: Sugar | B9: 50
A10: T-Shirt | B10: 20
A11: Tea Powder | B11: 40
A12: Total Result | B12: 240

Sheet Pivot_Sales_Salesperson
A1: Salesperson | B1: Sum - Sales
A2: Anjali | B2: 13300
A3: Arjun | B3: 13583
A4: Kiran | B4: 3000
A5: Neha | B5: 35982
A6: Priya | B6: 169200
A7: Rahul | B7: 624984
A8: Rohan | B8: 105600
A9: Sneha | B9: 230000
A10: Total Result | B10: 1195649

Sheet Pivot_profit_state
A1: State | B1: Sum - Profit
A2: Andhra Pradesh | B2: 24300
A3: Delhi | B3: 15840
A4: Gujarat | B4: 1995
A5: Karnataka | B5: 116094.6
A6: Kerala | B6: 3395.75
A7: Maharashtra | B7: 240
A8: Rajasthan | B8: 11195.52
A9: TamilNadu | B9: 3420
A10: Telangana | B10: 34500
A11: Total Result | B11: 210980.87

Sheet Pivot_Sales_Category
A1: Category | B1: Sum - Sales
A2: Clothing | B2: 89549
A3: Electronics | B3: 1055600
A4: Grocery | B4: 50500
A5: Total Result | B5: 1195649

Sheet  Product Quantity 

Sheet Sales by Salesperson

Sheet Profit by State

Sheet Sales by Category

Sheet Dashboard
G2: Retail Sales Dashboard
V3: Total sales | X3: Total Profit | Z3: Total Quantity
V4: 1195649 | X4: 210980.87 | Z4: 240
C54: Highest Sales Category : Electronics
C56: Most Profitable State : Karnataka
C58: Top Salesperson : Rahul
C60: Top Quantity Product : Sugar
